TaskManagerHandler/Shyna_bot_handler.py
TaskManagerHandler/Shyna_mom_apt.py
TaskManagerHandler/Shyna_set_alarm_apt.py
TaskManagerHandler/__init__.py
TaskManagerHandler/shyna_check_termux_online_apt.py
TaskManagerHandler/shyna_coin_toss_apt.py
TaskManagerHandler/shyna_get_joke_adapter.py
TaskManagerHandler/shyna_google_search_apt.py
TaskManagerHandler/shyna_intro_adapter.py
TaskManagerHandler/shyna_morning_apt.py
TaskManagerHandler/shyna_sleep_apt.py
TaskManagerHandler/shyna_weather_apt.py
TaskManagerHandler-0.0.2.dist-info/LICENSE
TaskManagerHandler-0.0.2.dist-info/METADATA
TaskManagerHandler-0.0.2.dist-info/WHEEL
TaskManagerHandler-0.0.2.dist-info/top_level.txt
TaskManagerHandler-0.0.2.dist-info/RECORD
