Metadata-Version: 2.1
Name: TaskManagerHandler
Version: 0.0.2
Summary: This package will take care of interacting with speech interactions.
Author: Shivam Sharma
Author-email: shivamsharma1913@gmail.com
License-File: LICENSE
Requires-Dist: setuptools
Requires-Dist: wheel
